COPYING
MANIFEST.in
README
health_calendar_view.xml
setup.py
./__init__.py
./health_calendar.py
./health_calendar_view.xml
./tryton.cfg
./doc/index.rst
./icons/calendar_icon.svg
./icons/execute_icon.svg
./locale/ar.po
./locale/de.po
./locale/el.po
./locale/es.po
./locale/fr.po
./locale/it_IT.po
./locale/ja_JP.po
./locale/lo.po
./locale/pt_BR.po
./locale/zh_CN.po
./tests/__init__.py
./tests/test_health_calendar.py
./view/gnuhealth_appointment_calendar.xml
./view/gnuhealth_calendar_appointment.xml
./view/gnuhealth_calendar_user.xml
./view/gnuhealth_create_appointment_start_form.xml
./wizard/__init__.py
./wizard/health_calendar_wizard.xml
./wizard/wizard_health_calendar.py
icons/README
icons/calendar_icon.svg
icons/execute_icon.svg
locale/ar.po
locale/de.po
locale/el.po
locale/es.po
locale/fr.po
locale/it_IT.po
locale/ja_JP.po
locale/lo.po
locale/pt_BR.po
locale/zh_CN.po
trytond_health_calendar.egg-info/PKG-INFO
trytond_health_calendar.egg-info/SOURCES.txt
trytond_health_calendar.egg-info/dependency_links.txt
trytond_health_calendar.egg-info/entry_points.txt
trytond_health_calendar.egg-info/not-zip-safe
trytond_health_calendar.egg-info/requires.txt
trytond_health_calendar.egg-info/top_level.txt
view/gnuhealth_appointment_calendar.xml
view/gnuhealth_calendar_appointment.xml
view/gnuhealth_calendar_user.xml
view/gnuhealth_create_appointment_start_form.xml
wizard/health_calendar_wizard.xml